Workbook

Sheet - AYUDA -
B4: Ayuda

Sheet Precios 
B5: Comparación de Precios entre diferentes proveedores
B6: Ingresa en la tabla los productos, los proveedores y sus precios
J7: ESTADÍSTICAS POR PRODUCTO
B8: PRODUCTO | C8: CANTIDAD | D8: Falabella | E8: Alkosto | F8: Mercado Libre | G8: PROVEEDOR 4 | H8: PROVEEDOR 5 | I8: PROVEEDOR 6 | J8: PRECIO MÁS BAJO | K8: PRECIO PROMEDIO | L8: PRECIO MÁS ALTO
B9: Torre admin | C9: 5 | D9: 950810 | E9: 702088 | F9: 1150899 | J9: =MIN('Precios '!$D9:$I9) -> 702088 | K9: =AVERAGE('Precios '!$D9:$F9) -> 934599 | L9: =MAX('Precios '!$D9:$I9) -> 1150899
B10: Monitor admin | C10: 5 | D10: 618681 | E10: 1070881 | F10: 485520 | J10: =MIN('Precios '!$D10:$I10) -> 485520 | K10: =IFERROR(AVERAGE('Precios '!$D10:$F10),"") -> 725027.33 | L10: =MAX('Precios '!$D10:$I10) -> 1070881
B11: Disco solido admin | C11: 5 | D11: 638316 | E11: 571081 | F11: 452081 | J11: =MIN('Precios '!$D11:$I11) -> 452081 | K11: =AVERAGE('Precios '!$D11:$F11) -> 553826 | L11: =MAX('Precios '!$D11:$I11) -> 638316
B12: Disco duro interno admin | C12: 5 | D12: 178381 | E12: 523481 | F12: 200991 | J12: =MIN('Precios '!$D12:$I12) -> 178381 | K12: =IFERROR(AVERAGE('Precios '!$D12:$F12),"") -> 300951 | L12: =MAX('Precios '!$D12:$I12) -> 523481
B13: Servidor admin | C13: 1 | D13: 9127145.3 | E13: 7852810 | F13: 10505831 | J13: =MIN('Precios '!$D13:$I13) -> 7852810 | K13: =IFERROR(AVERAGE('Precios '!$D13:$F13),"") -> 9161928.6 | L13: =MAX('Precios '!$D13:$I13) -> 10505831
B14: Ram amin | C14: 5 | D14: 172550 | E14: 208250 | F14: 296310 | J14: =MIN('Precios '!$D14:$I14) -> 172550 | K14: =IFERROR(AVERAGE('Precios '!$D14:$F14),"") -> 225703.33 | L14: =MAX('Precios '!$D14:$I14) -> 296310
B15: Teclado admin | C15: 5 | D15: 106981 | E15: 71281 | F15: 118881 | J15: =MIN('Precios '!$D15:$I15) -> 71281 | K15: =IFERROR(AVERAGE('Precios '!$D15:$F15),"") -> 99047.667 | L15: =MAX('Precios '!$D15:$I15) -> 118881
B16: Mouse admin | C16: 5 | D16: 118881 | E16: 95081 | F16: 190162 | J16: =MIN('Precios '!$D16:$I16) -> 95081 | K16: =IFERROR(AVERAGE('Precios '!$D16:$F16),"") -> 134708 | L16: =MAX('Precios '!$D16:$I16) -> 190162
B17: Software licencia | C17: 5 | D17: 1307810 | E17: 714000 | F17: 452448 | J17: =MIN('Precios '!$D17:$I17) -> 452448 | K17: =IFERROR(AVERAGE('Precios '!$D17:$F17),"") -> 824752.67 | L17: =MAX('Precios '!$D17:$I17) -> 1307810
B18: Licencia visual | C18: 1 | D18: 6480458 | E18: 107100 | F18: 0 | J18: =MIN('Precios '!$D18:$I18) -> 0 | K18: =IFERROR(AVERAGE('Precios '!$D18:$F18),"") -> 2195852.7 | L18: =MAX('Precios '!$D18:$I18) -> 6480458
B19: Licencia SQL | C19: 1 | D19: 2157565.2 | E19: 4470000 | F19: 4748100 | J19: =MIN('Precios '!$D19:$I19) -> 2157565.2 | K19: =IFERROR(AVERAGE('Precios '!$D19:$F19),"") -> 3791888.4 | L19: =MAX('Precios '!$D19:$I19) -> 4748100
B20: Hosting y dominio | C20: 1 | D20: 325798.2 | E20: 135267.3 | F20: 212058 | J20: =MIN('Precios '!$D20:$I20) -> 135267.3 | K20: =IFERROR(AVERAGE('Precios '!$D20:$F20),"") -> 224374.5 | L20: =MAX('Precios '!$D20:$I20) -> 325798.2
B21: Frontend | C21: 1 | D21: 1640772 | E21: 1640772 | F21: 1640772 | J21: =MIN('Precios '!$D21:$I21) -> 1640772 | K21: =IFERROR(AVERAGE('Precios '!$D21:$F21),"") -> 1640772 | L21: =MAX('Precios '!$D21:$I21) -> 1640772
B22: Backend | C22: 1 | D22: 1607656.7 | E22: 1607656.7 | F22: 2050965 | J22: =MIN('Precios '!$D22:$I22) -> 1607656.7 | K22: =IFERROR(AVERAGE('Precios '!$D22:$F22),"") -> 1755426.1 | L22: =MAX('Precios '!$D22:$I22) -> 2050965
B23: Total | D23: =ROUND(SUMPRODUCT('Precios '!$C$9:$C$22,'Precios '!$D$9:$D$22),2) -> 41801445 | E23: =ROUND(SUMPRODUCT('Precios '!$C$9:$C$22,'Precios '!$E$9:$E$22),2) -> 35594321 | F23: =ROUND(SUMPRODUCT('Precios '!$C$9:$C$22,'Precios '!$F$9:$F$22),2) -> 35894186 | G23: =ROUND(SUMPRODUCT('Precios '!$C$9:$C$19,'Precios '!$G$9:$G$19),2) -> 0 | H23: =ROUND(SUMPRODUCT('Precios '!$C$9:$C$19,'Precios '!$H$9:$H$19),2) -> 0 | I23: =ROUND(SUMPRODUCT('Precios '!$C$9:$C$19,'Precios '!$I$9:$I$19),2) -> 0
B26: DATOS ADICIONALES
B27: TIEMPO DE ENTREGA (DÍAS) | D27: Horas de dia los 7 dias de la semana | E27: de 3 a 5 minutos | F27: 3 a 10 dias habiles | G27: entrega de 2 dias habiles | H27: 1 a 5 dias habiles | I27: 5 dias laborales
B28: COSTO DE ENVÍO | D28: 0 | E28: $ 7.055 | F28: $287.497 | G28: 0 | H28: $295.39 | I28: 0
B29: FORMAS DE PAGO
D31: contado | E31: contado | F31: contado | G31: contado | H31: contado | I31: contado

Sheet Soporte
B7: Almendras | C7: 1 | D7: 498 | E7: 420 | F7: 450 | G7: 230 | H7: 600 | I7: 520
B8: Nueces | C8: 2 | D8: 450 | E8: 220 | F8: 405 | G8: 495 | H8: 540 | I8: 200
B9: Pistachos | C9: 2 | D9: 650 | E9: 620 | F9: 666 | G9: 400 | H9: 648 | I9: 452.4
B10: Pecán | C10: 1 | D10: 585 | E10: 558 | F10: 320 | G10: 360 | H10: 583.2 | I10: 407.16
B11: Bananas | C11: 3 | D11: 526.5 | E11: 502.2 | F11: 539.46 | G11: 300 | H11: 500 | I11: 366.44
B12: Pasas | C12: 1 | D12: 473.8 | E12: 200 | F12: 485.51 | G12: 291.6 | H12: 270 | I12: 220
D19: 30 | E19: 10 | F19: 15 | G19: 15 | H19: 15 | I19: 10
D20: 10 | E20: 10 | F20: 10 | G20: Gratis | H20: 5 | I20: Gratis
D21: Efvo | E21: Efvo | F21: Mercado Pago | G21: Efectivo | H21: Mercado Pago | I21: Mercado Pago
D22: Tarjeta | E22: Tarjeta | F22: Tarjeta cuotas | G22: Mercado Pago | H22: Tarjeta cuotas | I22: Tarjeta cuotas
B28: Piñones | C28: 1 | D28: 340 | E28: 330 | F28: 440 | G28: 400 | H28: 320 | I28: 330
B29: Cranberries | C29: 1 | D29: 220 | E29: 230 | F29: 240 | G29: 220 | H29: 219 | I29: 218
B30: Castañas | C30: 2 | D30: 560 | E30: 580 | F30: 550 | G30: 520 | H30: 551 | I30: 550
B35: China Co
B36: 250
B37: 440
B38: 440
B39: 350
B40: 420
B41: 199
